taskwarrior_inthe_am/__init__.py
taskwarrior_inthe_am/api.py
taskwarrior_inthe_am/cmdline.py
taskwarrior_inthe_am/commands.py
taskwarrior_inthe_am/exceptions.py
taskwarrior_inthe_am/taskwarrior.py
taskwarrior_inthe.am-1.1.2.dist-info/LICENSE
taskwarrior_inthe.am-1.1.2.dist-info/METADATA
taskwarrior_inthe.am-1.1.2.dist-info/WHEEL
taskwarrior_inthe.am-1.1.2.dist-info/entry_points.txt
taskwarrior_inthe.am-1.1.2.dist-info/top_level.txt
taskwarrior_inthe.am-1.1.2.dist-info/RECORD
