Metadata-Version: 2.1
Name: taskwarrior-inthe.am
Version: 1.1.2
Summary: Tools for making using Inthe.AM with Taskwarrior easier.
Home-page: https://github.com/coddingtonbear/taskwarrior-inthe.am
Author: Adam Coddington
Author-email: me@adamcoddington.net
License: UNKNOWN
Platform: UNKNOWN
Classifier: License :: OSI Approved :: MIT License
Classifier: Operating System :: OS Independent
Classifier: Programming Language :: Python :: 3
Requires-Dist: six
Requires-Dist: configobj (<6,>=5.0.6)
Requires-Dist: argparse (<2,>=1.2.1)
Requires-Dist: requests (<3,>=2.5.0)
Requires-Dist: keyring (<5,>=4.0)
Requires-Dist: taskw (==0.8.6)
